{
  "testMode": false,
  "moralisServerUrl": "https://ley6sxaeowsj.usemoralis.com:2053/server",
  "moralisMasterKey": "zkbVq5khThsj8tz4SVabhTQ72FrKYnyurhH1oJS1",
  "moralisApiKey": "scD0gQRnJbJ8pRrsVblt9fB5aDUHdQ0bLjCqbX75QBhQbNCA2JPIqASuV8ZEpDeI",
  "moralisSpeedyUrl": "https://speedy-nodes-nyc.moralis.io/297790e081b74c8e5b66d952/polygon/mainnet",
  "DBUsername": "Polygon-NFT-Parse",
  "DBPassword": "PolyParser",
  "DBClusterName": "Multi App Database Cluster",
  "DBName": "Polygon-NFT-Data",
  "sendNFTGasLimit": 250000,
  "sendNFTFunctionName": "safeTransferFrom",
  "sendNFTFunctionParams": [
    "",
    "#receiverAddress",
    "#tokenId",
    1,
    "0x00"
  ],
  "sendERC20FunctionName": "disperseTokenSimple",
  "sendERC20GasLimit": 10000000,
  "maxAddressPerERC20Send": 75,
  "sendERC20ContractAddress": "0x1b5e3e7B265E8Fa8Ee8c41ED07B046f0318E8412",
  "sendERC20ContractABI": [
    {
      "inputs": [
        {
          "internalType": "address[]",
          "name": "recipients",
          "type": "address[]"
        },
        {
          "internalType": "uint256[]",
          "name": "values",
          "type": "uint256[]"
        }
      ],
      "name": "disperseEther",
      "outputs": [],
      "stateMutability": "payable",
      "type": "function"
    },
    {
      "inputs": [
        {
          "internalType": "contract IERC20",
          "name": "token",
          "type": "address"
        },
        {
          "internalType": "address[]",
          "name": "recipients",
          "type": "address[]"
        },
        {
          "internalType": "uint256[]",
          "name": "values",
          "type": "uint256[]"
        }
      ],
      "name": "disperseToken",
      "outputs": [],
      "stateMutability": "nonpayable",
      "type": "function"
    },
    {
      "inputs": [
        {
          "internalType": "contract IERC20",
          "name": "token",
          "type": "address"
        },
        {
          "internalType": "address[]",
          "name": "recipients",
          "type": "address[]"
        },
        {
          "internalType": "uint256[]",
          "name": "values",
          "type": "uint256[]"
        }
      ],
      "name": "disperseTokenSimple",
      "outputs": [],
      "stateMutability": "nonpayable",
      "type": "function"
    }
  ]
}
